topsis.py
TOPSIS_GARVIT_101803122-0.0.1.dist-info/LICENSE.txt
TOPSIS_GARVIT_101803122-0.0.1.dist-info/METADATA
TOPSIS_GARVIT_101803122-0.0.1.dist-info/WHEEL
TOPSIS_GARVIT_101803122-0.0.1.dist-info/top_level.txt
TOPSIS_GARVIT_101803122-0.0.1.dist-info/RECORD
